<root>
    <item name='org.codehaus.groovy.control.io.NullWriter DEFAULT'>
        <annotation name='org.jetbrains.annotations.NotNull'/>
    </item>
    <item
        name='org.codehaus.groovy.control.io.StringReaderSource StringReaderSource(java.lang.String, org.codehaus.groovy.control.CompilerConfiguration) 1'>
        <annotation name='org.jetbrains.annotations.NotNull'/>
    </item>
    <item
        name='org.codehaus.groovy.control.io.FileReaderSource FileReaderSource(java.io.File, org.codehaus.groovy.control.CompilerConfiguration) 1'>
        <annotation name='org.jetbrains.annotations.NotNull'/>
    </item>
    <item name='org.codehaus.groovy.control.io.FileReaderSource java.io.Reader getReader()'>
        <annotation name='org.jetbrains.annotations.NotNull'/>
    </item>
    <item
        name='org.codehaus.groovy.control.io.InputStreamReaderSource InputStreamReaderSource(java.io.InputStream, org.codehaus.groovy.control.CompilerConfiguration) 1'>
        <annotation name='org.jetbrains.annotations.NotNull'/>
    </item>
    <item name='org.codehaus.groovy.control.io.URLReaderSource java.io.Reader getReader()'>
        <annotation name='org.jetbrains.annotations.NotNull'/>
    </item>
    <item
        name='org.codehaus.groovy.control.io.URLReaderSource URLReaderSource(java.net.URL, org.codehaus.groovy.control.CompilerConfiguration) 1'>
        <annotation name='org.jetbrains.annotations.NotNull'/>
    </item>
    <item name='org.codehaus.groovy.control.io.StringReaderSource java.io.Reader getReader()'>
        <annotation name='org.jetbrains.annotations.NotNull'/>
    </item>
    <item
        name='org.codehaus.groovy.control.io.AbstractReaderSource AbstractReaderSource(org.codehaus.groovy.control.CompilerConfiguration) 0'>
        <annotation name='org.jetbrains.annotations.NotNull'/>
    </item>
</root>
